parser_json_python/__init__.py
parser_json_python/fields.py
parser_json_python/parser.py
parser_json_python/tests.py
parser_json_python-1.0.1.dist-info/LICENSE
parser_json_python-1.0.1.dist-info/METADATA
parser_json_python-1.0.1.dist-info/WHEEL
parser_json_python-1.0.1.dist-info/top_level.txt
parser_json_python-1.0.1.dist-info/RECORD
