Metadata-Version: 2.1
Name: parser-json-python
Version: 1.0.1
Summary: The parser which can get dict with strings and convert them to Python types like int, float, date, list etc. It can be useful for parsing request params via API.
Home-page: https://github.com/eumozge/parser-json-python
Author: Eugene Mozge
Author-email: eumozge@gmail.com
License: UNKNOWN
Platform: UNKNOWN
Classifier: Development Status :: 5 - Production/Stable
Classifier: Programming Language :: Python :: 3
Classifier: License :: OSI Approved :: MIT License
Classifier: Operating System :: OS Independent
